[
{
    "pk": 1,
    "model": "auth.group",
    "fields": {
        "name": "Editors",
        "permissions": [
            [
                "can_delete",
                "fa_admin",
                "findingaids"
            ],
            [
                "can_prepare",
                "fa_admin",
                "findingaids"
            ],
            [
                "can_preview",
                "fa_admin",
                "findingaids"
            ],
            [
                "can_publish",
                "fa_admin",
                "findingaids"
            ],
            [
                "can_view_internal_dao",
                "fa_admin",
                "findingaids"
            ]
        ]
    }
},
{
    "pk": 2,
    "model": "auth.group",
    "fields": {
        "name": "Publishers",
        "permissions": [
            [
                "can_prepare",
                "fa_admin",
                "findingaids"
            ],
            [
                "can_preview",
                "fa_admin",
                "findingaids"
            ],
            [
                "can_publish",
                "fa_admin",
                "findingaids"
            ],
            [
                "can_view_internal_dao",
                "fa_admin",
                "findingaids"
            ]
        ]
    }
}
]
