<?xml version="1.0" encoding="utf-8"?>
<linkCollection xmlns:dc="http://purl.org/dc/elements/1.1/">
  <subjectList>
    <dc:subject>United States--History--Civil War, 1861-1865.</dc:subject>
    <dc:subject>United States--History--Civil War, 1861-1865--Foreign Public Opinion.</dc:subject>
    <dc:subject>Illustrated London News</dc:subject>
    </subjectList>

  <linkRecord id="2004-04-01%Rebecca Sutton Koeser">
        <dc:title>ILN Picture Library</dc:title>
        <dc:description>ILN picture repository. Expected to be fully searchable May 2004.</dc:description>
        <dc:date>2004-04-01</dc:date>
        <dc:contributor>Rebecca Sutton Koeser</dc:contributor>
        <dc:subject>Illustrated LondonNews</dc:subject>
        <dc:identifier>http://www.ilnpictures.co.uk/</dc:identifier>
    </linkRecord>

<linkRecord id="2004-04-06%Rebecca Sutton Koeser">
        <dc:title>Nineteenth Century Railway History through the Illustrated London News</dc:title>
        <dc:subject>Illustrated London News</dc:subject>
        <dc:description>A selection of railway-related ILN articles and illustrations.</dc:description>
        <dc:contributor>Rebecca Sutton Koeser</dc:contributor>
        <dc:date>2004-04-06</dc:date>
        <dc:identifier>http://www.mtholyoke.edu/courses/rschwart/ind_rev/iln/ilnhome.html</dc:identifier>
    </linkRecord>

    <linkRecord id="2004-04-09%Rebecca Sutton Koeser">
        <dc:title>American Civil War</dc:title>
        <dc:identifier>http://sunsite.utk.edu/civil-war/</dc:identifier>
        <dc:description>Sunsite website with many Civil War resources.</dc:description>
        <dc:date>2004-04-09 4:13 PM</dc:date>
        <dc:contributor>Rebecca Sutton Koeser</dc:contributor>
        <dc:subject>United States--History--Civil War, 1861-1865.</dc:subject>
    </linkRecord>

</linkCollection>
